ha_detect_geo_text/__init__.py
ha_detect_geo_text/example.py
ha_detect_geo_text_my1-1.dist-info/LICENCE
ha_detect_geo_text_my1-1.dist-info/METADATA
ha_detect_geo_text_my1-1.dist-info/WHEEL
ha_detect_geo_text_my1-1.dist-info/top_level.txt
ha_detect_geo_text_my1-1.dist-info/RECORD
